[
  {
    "content_id": 511277,
    "reference_id": 5807,
    "title": "اليونانية الكوينية",
    "media_type": "Text",
    "index_reference": "اليونانية الكوينية",
    "language": "arb",
    "content": "<h1>*اليونانية الكوينية</h1><p>نوع من اليونانية كان &quot;شائعًا&quot; <em>(معنى كلمة &quot;كويني&quot;)</em> في أراضي الشرق الأدنى وبلاد البحر المتوسط في العصور الرومانية. وهي اليونانية التي كُتب بها العهد الجديد. <em>انظر</em> <span data-bnType=\"resourceReference\" data-resourceId=\"3399\" data-resourceType=\"TyndaleBibleDictionary\">الكتاب المقدس</span>.</p>",
    "associations": {
      "passage": [],
      "resource": [
        {
          "reference_id": 3399,
          "content_id": 335194,
          "resource_code": "TyndaleBibleDictionary",
          "label": "الكتاب المقدس",
          "language": "arb"
        }
      ]
    }
  }
]