[
  {
    "content_id": 510713,
    "reference_id": 4939,
    "version": "1.0.0",
    "title": "حلبة",
    "media_type": "Text",
    "index_reference": "حلبة",
    "language": "arb",
    "content": "<h1>حلبة</h1><p>إحدى الحصون الكنعانية التي لم يتمكن سبط أشير من غزوها بعد أن استولى على الأرض (<a href=\"https://ref.ly/Judg1:31\">قضاة 1:31</a>).</p>",
    "associations": {
      "passage": [
        {
          "start_ref": "07001031",
          "start_ref_usfm": "JDG 1:31",
          "end_ref": "07001031",
          "end_ref_usfm": "JDG 1:31"
        }
      ],
      "resource": []
    }
  }
]