[
  {
    "content_id": 509479,
    "reference_id": 2889,
    "title": "خزائن (السجلات)",
    "media_type": "Text",
    "index_reference": "خزائن (السجلات)",
    "language": "arb",
    "content": "<h1>المحفوظات (السجلات)</h1><p>مجموعات من الوثائق أو السجلات المهمة التي يُحتفَظ بها لقيمتها التاريخية أو للرجوع إليها في المستقبل.</p><p>انظر <span data-bnType=\"resourceReference\" data-resourceId=\"5099\" data-resourceType=\"TyndaleBibleDictionary\">بيت الخزائن</span>.</p>",
    "associations": {
      "passage": [],
      "resource": [
        {
          "reference_id": 5099,
          "content_id": 510820,
          "resource_code": "TyndaleBibleDictionary",
          "label": "بيت الخزائن",
          "language": "arb"
        }
      ]
    }
  }
]