[
  {
    "content_id": 510141,
    "reference_id": 3974,
    "title": "ديماس",
    "media_type": "Text",
    "index_reference": "ديماس",
    "language": "arb",
    "content": "<h1>ديماس</h1><p>أحد العاملين مع الرسول بولس. وقد كان مع بولس عندما كان مسجونًا. لا يُعرَف الكثير عن ديماس باستثناء المعلومات البسيطة المذكورة في العهد الجديد. ففي البداية، أيَّد ديماس خدمة بولس. وقد ذُكر في تحية بولس إلى أهل كولوسي في <a href=\"https://ref.ly/Col4:14\">كولوسي 4: 14</a>. كما ذُكر في <a href=\"https://ref.ly/Phlm1:24\">فليمون 1: 24</a>. لكن في <a href=\"https://ref.ly/2Tim4:10\">2تيموثاوس 4: 10</a> قال بولس إن ديماس تركه بسبب محبة ديماس للعالم الحاضر.</p>",
    "associations": {
      "passage": [
        {
          "start_ref": "51004014",
          "start_ref_usfm": "COL 4:14",
          "end_ref": "51004014",
          "end_ref_usfm": "COL 4:14"
        },
        {
          "start_ref": "55004010",
          "start_ref_usfm": "2TI 4:10",
          "end_ref": "55004010",
          "end_ref_usfm": "2TI 4:10"
        },
        {
          "start_ref": "57001024",
          "start_ref_usfm": "PHM 1:24",
          "end_ref": "57001024",
          "end_ref_usfm": "PHM 1:24"
        }
      ],
      "resource": []
    }
  }
]