[
  {
    "content_id": 512272,
    "reference_id": 7539,
    "version": "1.0.0",
    "title": "شَفوفَان",
    "media_type": "Text",
    "index_reference": "شَفوفَان",
    "language": "arb",
    "content": "<h1><span>شَفُوفَان</span></h1><p>ابن بالع بكر بنيامين بن يعقوب (<a href=\"https://ref.ly/1Chr8:5\">1&nbsp;أخبار 8:5</a>)، ولكن موقع شفوفان الدقيق ضمن نسل بنيامين غير واضح، ولكن ربما يمكن ربطه بشفيم (<a href=\"https://ref.ly/1Chr7:12\">1&nbsp;أخبار 7:12</a>).</p>",
    "associations": {
      "passage": [
        {
          "start_ref": "13007012",
          "start_ref_usfm": "1CH 7:12",
          "end_ref": "13007012",
          "end_ref_usfm": "1CH 7:12"
        },
        {
          "start_ref": "13008005",
          "start_ref_usfm": "1CH 8:5",
          "end_ref": "13008005",
          "end_ref_usfm": "1CH 8:5"
        }
      ],
      "resource": []
    }
  }
]