[
  {
    "content_id": 331888,
    "reference_id": 6009,
    "title": "مَديان",
    "media_type": "Text",
    "index_reference": "مَديان",
    "language": "arb",
    "content": "<h1>مَديان*</h1><p>تهجئة أخرى لكلمة مِديان، وهي منطقة جغرافية تقع شمال غرب شبه الجزيرة العربية، ورد ذكرها في <a href=\"https://ref.ly/Acts7:29\">أعمال الرسل 7:29</a>. انظر <span data-bnType=\"resourceReference\" data-resourceId=\"6290\" data-resourceType=\"TyndaleBibleDictionary\">مِديان، مِدياني</span>.</p>",
    "associations": {
      "passage": [
        {
          "start_ref": "44007029",
          "start_ref_usfm": "ACT 7:29",
          "end_ref": "44007029",
          "end_ref_usfm": "ACT 7:29"
        }
      ],
      "resource": [
        {
          "reference_id": 6290,
          "content_id": 443896,
          "resource_code": "TyndaleBibleDictionary",
          "label": "مِدْيَان، المِدْيَانِيُّون",
          "language": "arb"
        }
      ]
    }
  }
]