[
  {
    "content_id": 511705,
    "reference_id": 6538,
    "version": "1.0.0",
    "title": "نَتَاعِيم",
    "media_type": "Text",
    "index_reference": "نَتَاعِيم",
    "language": "arb",
    "content": "<h1><strong>نَتَاعِيم</strong></h1><p>مكان إقامة الخزافين الذين تم توظيفهم لخدمة الملك (<a href=\"https://ref.ly/1Chr4:23\">1أخبار الأيام 4: 23</a>).</p>",
    "associations": {
      "passage": [
        {
          "start_ref": "13004023",
          "start_ref_usfm": "1CH 4:23",
          "end_ref": "13004023",
          "end_ref_usfm": "1CH 4:23"
        }
      ],
      "resource": []
    }
  }
]