[
  {
    "content_id": 443910,
    "reference_id": 6456,
    "version": "1.0.0",
    "title": "نَحَث",
    "media_type": "Text",
    "index_reference": "نَحَث",
    "language": "arb",
    "content": "<h1><span>نَحَث</span></h1><p>١. أمير عشيرة في أَدُوم وابن رَعُوِئِيل البكر (<a href=\"https://ref.ly/Gen36:13,Gen36:17\">تكوين 36: 13، 17</a>؛ <a href=\"https://ref.ly/1Chr1:37\">1 أخبار 1: 37</a>).</p><p>2. لاوٍ من عشيرة قَهَات وحفيد أَلْقَانَة (<a href=\"https://ref.ly/1Chr6:26\">1&nbsp;أخبار 6:26</a>).</p><p>3. لاوٍ أشرف على أعمال الهيكل خلال حكم الملك حَزَقِيَّا (<a href=\"https://ref.ly/2Chr31:13\">2&nbsp;أخبار 31:13</a>).</p>",
    "associations": {
      "passage": [
        {
          "start_ref": "01036013",
          "start_ref_usfm": "GEN 36:13",
          "end_ref": "01036013",
          "end_ref_usfm": "GEN 36:13"
        },
        {
          "start_ref": "01036017",
          "start_ref_usfm": "GEN 36:17",
          "end_ref": "01036017",
          "end_ref_usfm": "GEN 36:17"
        },
        {
          "start_ref": "13001037",
          "start_ref_usfm": "1CH 1:37",
          "end_ref": "13001037",
          "end_ref_usfm": "1CH 1:37"
        },
        {
          "start_ref": "13006026",
          "start_ref_usfm": "1CH 6:26",
          "end_ref": "13006026",
          "end_ref_usfm": "1CH 6:26"
        },
        {
          "start_ref": "14031013",
          "start_ref_usfm": "2CH 31:13",
          "end_ref": "14031013",
          "end_ref_usfm": "2CH 31:13"
        }
      ],
      "resource": []
    }
  }
]