[
  {
    "content_id": 512567,
    "reference_id": 8014,
    "version": "1.0.0",
    "title": "وقت، زمن",
    "media_type": "Text",
    "index_reference": "وقت، زمن",
    "language": "arb",
    "content": "<h1>وقت، زمن</h1><p>انظر <span data-bnType=\"resourceReference\" data-resourceId=\"3559\" data-resourceType=\"TyndaleBibleDictionary\">التقويمات القديمة والحديثة</span>.</p>",
    "associations": {
      "passage": [],
      "resource": [
        {
          "reference_id": 3559,
          "content_id": 331755,
          "resource_code": "TyndaleBibleDictionary",
          "label": "التقاويم، القديمة والحديثة",
          "language": "arb"
        }
      ]
    }
  }
]