[
  {
    "content_id": 511116,
    "reference_id": 5530,
    "version": "1.0.0",
    "title": "يَعِيئِيل",
    "media_type": "Text",
    "index_reference": "يَعِيئِيل",
    "language": "arb",
    "content": "<h1><span>يَعِيئِيل</span></h1><p>1. من نسل يهوذا أقام في أورشليم بعد السبي (<a href=\"https://ref.ly/1Chr9:6\">1&nbsp;أخ 9:6</a>).</p><p>2. اللاوي الذي شارك في إصلاحات الملك حزقيا (<a href=\"https://ref.ly/2Chr29:13\">2&nbsp;أخ 29:13</a>).</p><p>٣. رئيس عائلة عاد إلى أورشليم مع عزرا بعد السبي (<a href=\"https://ref.ly/Ezra8:13\">عز ٨: ١٣</a>).</p>",
    "associations": {
      "passage": [
        {
          "start_ref": "13009006",
          "start_ref_usfm": "1CH 9:6",
          "end_ref": "13009006",
          "end_ref_usfm": "1CH 9:6"
        },
        {
          "start_ref": "14029013",
          "start_ref_usfm": "2CH 29:13",
          "end_ref": "14029013",
          "end_ref_usfm": "2CH 29:13"
        },
        {
          "start_ref": "15008013",
          "start_ref_usfm": "EZR 8:13",
          "end_ref": "15008013",
          "end_ref_usfm": "EZR 8:13"
        }
      ],
      "resource": []
    }
  }
]