[
  {
    "content_id": 335321,
    "reference_id": 5444,
    "title": "يَهُويَاكِينُ",
    "media_type": "Text",
    "index_reference": "يَهُويَاكِينُ",
    "language": "arb",
    "content": "<h1><span>يَهُويَاكِين</span></h1><p>كان <span>يَهُويَاكِين</span> ملك يهوذا لفترة قصيرة جدًا، حيث حكم من 598 إلى 597 ق.م. كان ابن <span>يَهُويَاقِيم</span> و<span>نَحُوشْتَا بنت أَلِنَاثَان</span> من أورشليم (ربما نفس <span>أَلْنَاثَان</span> الذي ذكره النبي إرميا، انظر <a href=\"https://ref.ly/Jer26:22\">إرميا 26: 22؛ </a><a href=\"https://ref.ly/Jer36:12\">36: 12، 2</a>). يعني اسم يَهُويَاكِين &quot;يهوه سيحفظ.&quot; يُعرف أيضًا بأسماء أخرى مثل:</p><ul><li><p><span>كُنْيَاهُو</span> (<a href=\"https://ref.ly/Jer22:24\">إرميا 22: 24، 28؛ </a><a href=\"https://ref.ly/Jer37:1\">37: ١</a>)</p></li><li><p><span>يَكُنْيَا</span> (<a href=\"https://ref.ly/1Chr3:16-1Chr3:17\">1 أخبار 3: 16–17؛</a> <a href=\"https://ref.ly/Esth2:6\">أستير 2؛ 6؛</a> <a href=\"https://ref.ly/Jer24:1\">إرميا 24: 1؛</a> <a href=\"https://ref.ly/Jer27:20\">27: 20؛</a> <a href=\"https://ref.ly/Jer28:4\">28: 4؛</a> <a href=\"https://ref.ly/Jer29:2\">29: 2</a>)</p></li><li><p><span>يَكُنْيَا</span> (<a href=\"https://ref.ly/Matt1:11-Matt1:12\">متى 1: 11–12</a>).</p></li></ul><p>كان يَهُويَاكِين يبلغ من العمر 18 عامًا حين أصبح ملكًا بعد موت والده، لكنه حكم مدة ثلاثة أشهر وعشرة أيام فقط في أورشليم (<a href=\"https://ref.ly/2Kgs24:8\">2ملوك 24: 8؛</a> قارن  <a href=\"https://ref.ly/2Chr36:9\">2أخبار  36: 9</a>). في ذلك الوقت، كانت يهوذا تحت سيطرة بابل، لكنها كانت تتمرد عليها. عندما هاجم الملك البابلي <span>نَبُوخَذْنَاصَّر</span> أورشليم، اضطر يَهُويَاكِين للاستسلام لأنَّ الهزيمة كانت حتمية. وفقًا للسجل البابلي، الذي يستند إلى السجلات الرسمية لملوك بابل، دخل نَبُوخَذْنَاصَّر المنطقة في ديسمبر 598 ق.م. واحتل أورشليم في 16 مارس 597 ق.م. أفرغ البابليون خزائن القصر والهيكل. أخذ البابليون كثيرين من الأسرى إلى بابل:</p><ul><li><p>يَهُويَاكِين</p></li><li><p>عائلته</p></li><li><p>القادة العسكريين</p></li><li><p>مسؤلي البلاط الملكي</p></li><li><p>العُمّال المَهرة</p></li></ul><p>قبل العودة إلى بابل، نصَّب نَبُوخَذْنَاصَّر عم يَهُويَاكِين، <span>مَتَّنِيَّا</span>، الذي تغيّر اسمه إلى <span>صِدْقِيَّا</span>، على عرش أورشليم (<a href=\"https://ref.ly/2Kgs24:12-2Kgs24:17\">2ملوك 24: 12–17؛</a> قارن <a href=\"https://ref.ly/2Chr36:10\">2أخبار 36: 10</a>).</p><p>رأى إرميا النبي أنه على الرغم من ألم الغزو البابلي والفوضى السياسية الحاصلة، لم يختبر شعب يهوذا تغييرًا روحيًا كبيرًا (<a href=\"https://ref.ly/Jer37:1-Jer38:28\">إرميا 37–38</a>). كما تنبأ إرميا بأن يَهُويَاكِين سيؤخذ إلى السبي ولن يخلفه أي من نسله كملك (<a href=\"https://ref.ly/Jer22:24-Jer22:30\">إرميا 22: 24–30</a>). في المقابل، تنبأ نبي كاذب يدعى <span>حَنَنِيَّا</span> بأن يَهُويَاكِين سيستعيد  العرش في غضون عامين (<a href=\"https://ref.ly/Jer28:3-Jer28:4\">إرميا 28: 3–4، 11؛</a> قارن الآيات <a href=\"https://ref.ly/Jer28:12-Jer28:17\">12–17</a>).</p><p>ظل يَهُويَاكِين الملك الشرعي ليهوذا، وهذا ينعكس في حقيقة أنَّ النبي حزقيال كان يؤرخ رسائله وفقًا لسنوات سبي يَهُويَاكِين، وليس بحكم صِدْقِيَّا (<a href=\"https://ref.ly/Ezek1:2\">حزقيال 1: 2؛</a> <a href=\"https://ref.ly/Ezek8:1\">8: 1؛</a> <a href=\"https://ref.ly/Ezek20:1\">20: 1</a>). كما تعترف السجلات البابلية بمكانة يَهُويَاكِين الملكية. تُظهر هذه السجلات أنه احتفظ بلقبه كملك وتلقى معاملة مميزة من البابليين. حتى أنَّ إحدى اللوحات المسمارية سجلت &quot;ياوكين، ملك أرض يهوذا&quot;، مع أبنائه الخمسة، يتلقون حصصًا من الزيت والشعير. وهذا يشير إلى أنهم لم يكونوا مسجونين بل عاشوا حياة طبيعية نسبيًا في بابل. ومع ذلك، في مرحلة ما، سُجن يَهُويَاكِين. ثم أُطلق سراحه لاحقًا خلال حكم <span>أَوِيل مَرُودَخُ </span>حوالي 562 ق.م. ومُنح امتياز تناول الطعام مع الملك البابلي (<a href=\"https://ref.ly/2Kgs25:27-2Kgs25:30\">2ملوك 25: 27–30؛</a> <a href=\"https://ref.ly/Jer52:31-Jer52:34\">إرميا 52: 31–34</a>). لا يتضح سبب سجنه إذا ما كان نتيجة محاولة الهرب أو بسبب تمرد يهوذا ضد بابل تحت حكم صِدْقِيَّا.</p><p>يظهر اسم يَهُويَاكِين في قائمة عائلة يسوع المسيح في إنجيل متى (<a href=\"https://ref.ly/Matt1:11-Matt1:12\">متى 1: 11–12</a>). يعتقد البعض أنَّ هذا يتناقض مع نبوءة إرميا بألّا يجلس أحد من نسل يَهُويَاكِين على العرش (<a href=\"https://ref.ly/Jer22:30\">إرميا 22: 30</a>). ومع ذلك، يفترض آخرون أنَّ بركة <span>زَرُبَّابِل</span> (وهو من نسل يَهُويَاكِين) على لسان النبي حجي (<a href=\"https://ref.ly/Hag2:20-Hag2:23\">حجي 2: 20–23</a>) قد أبطلت لعنة إرميا وأعادت إدخال نسل يَهُويَاكِين في نسل داوُد، ومن ثمَّ النسل المسيّاني (انظر <a href=\"https://ref.ly/Isa56:3-Isa56:5\">إشعياء 56: 3–5</a>).</p><p><em>انظر أيضًا</em> <span data-bnType=\"resourceReference\" data-resourceId=\"3720\" data-resourceType=\"TyndaleBibleDictionary\">التسلسل الزمني للكتاب المقدَّس (العهد القديم)</span>؛ <span data-bnType=\"resourceReference\" data-resourceId=\"3999\" data-resourceType=\"TyndaleBibleDictionary\">شتات اليهود</span>؛ <span data-bnType=\"resourceReference\" data-resourceId=\"5260\" data-resourceType=\"TyndaleBibleDictionary\">إسرائيل، تاريخ</span>.</p>",
    "associations": {
      "passage": [
        {
          "start_ref": "12024008",
          "start_ref_usfm": "2KI 24:8",
          "end_ref": "12024008",
          "end_ref_usfm": "2KI 24:8"
        },
        {
          "start_ref": "14036009",
          "start_ref_usfm": "2CH 36:9",
          "end_ref": "14036009",
          "end_ref_usfm": "2CH 36:9"
        },
        {
          "start_ref": "14036010",
          "start_ref_usfm": "2CH 36:10",
          "end_ref": "14036010",
          "end_ref_usfm": "2CH 36:10"
        },
        {
          "start_ref": "17002006",
          "start_ref_usfm": "EST 2:6",
          "end_ref": "17002006",
          "end_ref_usfm": "EST 2:6"
        },
        {
          "start_ref": "24022024",
          "start_ref_usfm": "JER 22:24",
          "end_ref": "24022024",
          "end_ref_usfm": "JER 22:24"
        },
        {
          "start_ref": "24022028",
          "start_ref_usfm": "JER 22:28",
          "end_ref": "24022028",
          "end_ref_usfm": "JER 22:28"
        },
        {
          "start_ref": "24022030",
          "start_ref_usfm": "JER 22:30",
          "end_ref": "24022030",
          "end_ref_usfm": "JER 22:30"
        },
        {
          "start_ref": "24024001",
          "start_ref_usfm": "JER 24:1",
          "end_ref": "24024001",
          "end_ref_usfm": "JER 24:1"
        },
        {
          "start_ref": "24026022",
          "start_ref_usfm": "JER 26:22",
          "end_ref": "24026022",
          "end_ref_usfm": "JER 26:22"
        },
        {
          "start_ref": "24027020",
          "start_ref_usfm": "JER 27:20",
          "end_ref": "24027020",
          "end_ref_usfm": "JER 27:20"
        },
        {
          "start_ref": "24028004",
          "start_ref_usfm": "JER 28:4",
          "end_ref": "24028004",
          "end_ref_usfm": "JER 28:4"
        },
        {
          "start_ref": "24028011",
          "start_ref_usfm": "JER 28:11",
          "end_ref": "24028011",
          "end_ref_usfm": "JER 28:11"
        },
        {
          "start_ref": "24029002",
          "start_ref_usfm": "JER 29:2",
          "end_ref": "24029002",
          "end_ref_usfm": "JER 29:2"
        },
        {
          "start_ref": "24036012",
          "start_ref_usfm": "JER 36:12",
          "end_ref": "24036012",
          "end_ref_usfm": "JER 36:12"
        },
        {
          "start_ref": "24036025",
          "start_ref_usfm": "JER 36:25",
          "end_ref": "24036025",
          "end_ref_usfm": "JER 36:25"
        },
        {
          "start_ref": "24037001",
          "start_ref_usfm": "JER 37:1",
          "end_ref": "24037001",
          "end_ref_usfm": "JER 37:1"
        },
        {
          "start_ref": "26001002",
          "start_ref_usfm": "EZK 1:2",
          "end_ref": "26001002",
          "end_ref_usfm": "EZK 1:2"
        },
        {
          "start_ref": "26008001",
          "start_ref_usfm": "EZK 8:1",
          "end_ref": "26008001",
          "end_ref_usfm": "EZK 8:1"
        },
        {
          "start_ref": "26020001",
          "start_ref_usfm": "EZK 20:1",
          "end_ref": "26020001",
          "end_ref_usfm": "EZK 20:1"
        },
        {
          "start_ref": "23056003",
          "start_ref_usfm": "ISA 56:3",
          "end_ref": "23056005",
          "end_ref_usfm": "ISA 56:5"
        },
        {
          "start_ref": "12025027",
          "start_ref_usfm": "2KI 25:27",
          "end_ref": "12025030",
          "end_ref_usfm": "2KI 25:30"
        },
        {
          "start_ref": "24052031",
          "start_ref_usfm": "JER 52:31",
          "end_ref": "24052034",
          "end_ref_usfm": "JER 52:34"
        },
        {
          "start_ref": "40001011",
          "start_ref_usfm": "MAT 1:11",
          "end_ref": "40001012",
          "end_ref_usfm": "MAT 1:12"
        },
        {
          "start_ref": "13003016",
          "start_ref_usfm": "1CH 3:16",
          "end_ref": "13003017",
          "end_ref_usfm": "1CH 3:17"
        },
        {
          "start_ref": "12024012",
          "start_ref_usfm": "2KI 24:12",
          "end_ref": "12024017",
          "end_ref_usfm": "2KI 24:17"
        },
        {
          "start_ref": "24037001",
          "start_ref_usfm": "JER 37:1",
          "end_ref": "24038028",
          "end_ref_usfm": "JER 38:28"
        },
        {
          "start_ref": "24022024",
          "start_ref_usfm": "JER 22:24",
          "end_ref": "24022030",
          "end_ref_usfm": "JER 22:30"
        },
        {
          "start_ref": "24028003",
          "start_ref_usfm": "JER 28:3",
          "end_ref": "24028004",
          "end_ref_usfm": "JER 28:4"
        },
        {
          "start_ref": "24028012",
          "start_ref_usfm": "JER 28:12",
          "end_ref": "24028017",
          "end_ref_usfm": "JER 28:17"
        },
        {
          "start_ref": "37002020",
          "start_ref_usfm": "HAG 2:20",
          "end_ref": "37002023",
          "end_ref_usfm": "HAG 2:23"
        }
      ],
      "resource": [
        {
          "reference_id": 3720,
          "content_id": 335217,
          "resource_code": "TyndaleBibleDictionary",
          "label": "تسلسل زمني للكتاب المقدس (العهد القديم)",
          "language": "arb"
        },
        {
          "reference_id": 3999,
          "content_id": 232567,
          "resource_code": "TyndaleBibleDictionary",
          "label": "شتات اليهود",
          "language": "arb"
        },
        {
          "reference_id": 5260,
          "content_id": 232582,
          "resource_code": "TyndaleBibleDictionary",
          "label": "تاريخ إسرائيل",
          "language": "arb"
        }
      ]
    }
  }
]