[
  {
    "content_id": 806623,
    "reference_id": 5264,
    "version": "1.0.0",
    "title": "Isacar (Persona)",
    "media_type": "Text",
    "index_reference": "isacar (persona)",
    "language": "spa",
    "content": "<h1>ISACAR (Persona)</h1><p>1. El noveno hijo de Jacob y el quinto de su esposa Lea (<a href=\"https://ref.ly/Gen30:17-Gen30:18\">Gn 30:17–18</a>); su nombre posiblemente significa &quot;recompensa&quot;. Jacob, en su mensaje final a sus 12 hijos, dice: &quot;Isacar, <span>asno huesudo echado entre dos tercios&quot;</span> (<a href=\"https://ref.ly/Gen49:14\">49:14</a>, nasb); la imagen sugerida es la de un burro cargado que se niega a mover su carga, un hombre perezoso que no está dispuesto a hacer su parte del trabajo. Se sabe poco sobre Isacar, excepto lo que hizo junto con los otros hijos de Israel. Tuvo cuatro hijos (<a href=\"https://ref.ly/Gen46:13\">46:13</a>), quienes encabezaron clanes en la tribu (<a href=\"https://ref.ly/1Chr7:1-1Chr7:5\">1 Cro 7:1–5</a>). Su familia fue con Jacob a Egipto, donde murieron (aunque los restos de Isacar fueron posteriormente trasladados a Siquem junto con los otros 12 patriarcas—<a href=\"https://ref.ly/Acts7:16\">Hechos 7:16</a>).</p><p>Los descendientes de Isacar eran 54400 en el primer censo (<a href=\"https://ref.ly/Num1:29\">Nm 1:29</a>), aumentaron a 64300 en el segundo (<a href=\"https://ref.ly/Num26:25\">26:25</a>), y a 87000 durante el reinado de David (<a href=\"https://ref.ly/1Chr7:5\">1 Cro 7:5</a>). Isacar fue la tribu principal involucrada en la lucha liderada por Débora, quien era miembro de la tribu (<a href=\"https://ref.ly/Judg5:15\">Jc 5:15</a>). Durante el tiempo de David, había hombres de la tribu de Isacar que comprendían lo que Israel debía hacer en la guerra (<a href=\"https://ref.ly/1Chr12:32\">1 Cro 12:32</a>). Estos hombres apoyaron a David como rey para reemplazar a Saúl.</p><p>Isacar recibió el cuarto lote de tierra después de que el arca fue llevada a Silo (<a href=\"https://ref.ly/Josh19:17\">Jos 19:17</a>). Esto incluía las ciudades de Jezreel, Sunem y Ein Ganim, y se encontraba entre las montañas de Gilboa y Tabor. Su asignación estaba delimitada al sur y al oeste por la tribu de Manasés, al norte por Zabulón y Neftalí, y al este por el río Jordán. Este territorio era en gran parte una llanura fértil y a menudo era amenazado por los cananeos cercanos, así como por invasores extranjeros.</p><p>2. El hijo de Obed-Edom, quien fue un portero levita durante el reinado de David (<a href=\"https://ref.ly/1Chr26:5\">1 Crónicas 26:5</a>).</p>",
    "associations": {
      "passage": [
        {
          "start_ref": "01046013",
          "start_ref_usfm": "GEN 46:13",
          "end_ref": "01046013",
          "end_ref_usfm": "GEN 46:13"
        },
        {
          "start_ref": "01049014",
          "start_ref_usfm": "GEN 49:14",
          "end_ref": "01049014",
          "end_ref_usfm": "GEN 49:14"
        },
        {
          "start_ref": "04001029",
          "start_ref_usfm": "NUM 1:29",
          "end_ref": "04001029",
          "end_ref_usfm": "NUM 1:29"
        },
        {
          "start_ref": "04026025",
          "start_ref_usfm": "NUM 26:25",
          "end_ref": "04026025",
          "end_ref_usfm": "NUM 26:25"
        },
        {
          "start_ref": "06019017",
          "start_ref_usfm": "JOS 19:17",
          "end_ref": "06019017",
          "end_ref_usfm": "JOS 19:17"
        },
        {
          "start_ref": "07005015",
          "start_ref_usfm": "JDG 5:15",
          "end_ref": "07005015",
          "end_ref_usfm": "JDG 5:15"
        },
        {
          "start_ref": "13007005",
          "start_ref_usfm": "1CH 7:5",
          "end_ref": "13007005",
          "end_ref_usfm": "1CH 7:5"
        },
        {
          "start_ref": "13012032",
          "start_ref_usfm": "1CH 12:32",
          "end_ref": "13012032",
          "end_ref_usfm": "1CH 12:32"
        },
        {
          "start_ref": "13026005",
          "start_ref_usfm": "1CH 26:5",
          "end_ref": "13026005",
          "end_ref_usfm": "1CH 26:5"
        },
        {
          "start_ref": "44007016",
          "start_ref_usfm": "ACT 7:16",
          "end_ref": "44007016",
          "end_ref_usfm": "ACT 7:16"
        },
        {
          "start_ref": "01030017",
          "start_ref_usfm": "GEN 30:17",
          "end_ref": "01030018",
          "end_ref_usfm": "GEN 30:18"
        },
        {
          "start_ref": "13007001",
          "start_ref_usfm": "1CH 7:1",
          "end_ref": "13007005",
          "end_ref_usfm": "1CH 7:5"
        }
      ],
      "resource": []
    }
  }
]