[
  {
    "content_id": 471355,
    "reference_id": 8135,
    "version": "1.0.0",
    "title": "不可赦免的罪",
    "media_type": "Text",
    "index_reference": "不可赦免的罪",
    "language": "zht",
    "content": "<h1>不可赦免的罪</h1><p>將聖靈通過耶穌基督所展現的工作歸功給撒但。這種罪是褻瀆聖靈。</p><p>不可赦免的罪必須根據其上下文來理解，這可以在<a href=\"https://ref.ly/Matt12:31-Matt12:32\">馬太福音十二章31至32節</a>和<a href=\"https://ref.ly/Mark3:28-Mark3:30\">馬可福音三章28至30節</a>中找到。在這些經文中，耶穌剛剛從一個又瞎又啞的人身上趕出了一個鬼，無可爭辯地顯示出神的大能。但法利賽人因為頑固的不信，將這種神大能的顯現歸功於別西卜，就是魔鬼（<a href=\"https://ref.ly/Matt12:24\">太12:24</a>）。幾處經文揭示，許多猶太人表達了同樣錯誤的看法，認為耶穌藉著魔鬼的能力行神蹟（<a href=\"https://ref.ly/Matt9:34\">太9:34</a>；<a href=\"https://ref.ly/Matt11:18\">11:18</a>；<a href=\"https://ref.ly/Luke7:33\">路7:33，</a><a href=\"https://ref.ly/Luke11:14-Luke11:20\">11:14–20</a>；<a href=\"https://ref.ly/John7:20\">約7:20，</a><a href=\"https://ref.ly/John8:48,John8:52\">8:48、52，</a><a href=\"https://ref.ly/John10:20\">10:20</a>）。一群猶太人（主要是法利賽人）犯了將聖靈通過主耶穌所顯示的工作歸功給魔鬼的罪。當他們說耶穌由聖靈的力量完成的工作，是源自別西卜（即魔鬼），他們便犯了<em>不可赦免的</em>罪。簡而言之，他們大膽地將耶穌的工作描述為來自於魔鬼，因此犯下了嚴重的罪。令人關注的是，許多猶太人在耶穌死後仍延續這一錯誤指控。他們並未否認耶穌行了神蹟，而是聲稱衪所行的神蹟是出於魔鬼的力量。</p><h2>什麼不是不可赦免的罪</h2><p>不可赦免的罪不是以色列對神的悖逆，儘管這種叛逆導致成千上萬人受到永遠的審判和神的祝福暫時被撤回。約翰提到的「至於死的罪」（<a href=\"https://ref.ly/1John5:16-1John5:17\">約一5:16–17</a>）並不是不可赦免的罪。對一位已經得著救贖和罪的赦免（<a href=\"https://ref.ly/Eph1:7\">弗1:7</a>），並得著現今和將來罪的潔淨（<a href=\"https://ref.ly/1John1:7\">約一1:7</a>）且擁有永生（<a href=\"https://ref.ly/John3:16\">約3:16</a>）的人來說，不可能犯下不可赦免的罪。但那些犯下「至於死的罪」的人都是基督徒。<a href=\"https://ref.ly/1John5:16\">約翰壹書五章16節</a>說犯下「至於死的罪」的人是在基督裡的「弟兄」。</p><p>不可赦免的罪不是拒絕主耶穌，除非拒絕者在不信中去世。這樣的罪在永恆中不會被饒恕，但這並不等同於耶穌所指的不可赦免的罪：「凡說話干犯人子的，還可得赦免；惟獨說話干犯聖靈的，今世來世總不得赦免」（<a href=\"https://ref.ly/Matt12:32\">太12:32</a>）。許多經文反覆警告，不信救主將導致永遠的死亡（<a href=\"https://ref.ly/John3:18,John3:36\">約3:18、36</a>；<a href=\"https://ref.ly/1John5:12\">約一5:12</a>；<a href=\"https://ref.ly/Rev20:15\">啟20:15，</a><a href=\"https://ref.ly/Rev21:8\">21:8</a>），但這些經文並未直接指不可赦免的罪。耶穌斷言，一個人可以不信祂，甚至說話干犯祂，卻不一定犯了不可赦免的罪。</p><p><em>另見</em> <span data-bnType=\"resourceReference\" data-resourceId=\"5672\" data-resourceType=\"TyndaleBibleDictionary\">稱義、被稱義，</span><span data-bnType=\"resourceReference\" data-resourceId=\"7689\" data-resourceType=\"TyndaleBibleDictionary\">至死的罪</span>。</p>",
    "associations": {
      "passage": [
        {
          "start_ref": "40009034",
          "start_ref_usfm": "MAT 9:34",
          "end_ref": "40009034",
          "end_ref_usfm": "MAT 9:34"
        },
        {
          "start_ref": "40011018",
          "start_ref_usfm": "MAT 11:18",
          "end_ref": "40011018",
          "end_ref_usfm": "MAT 11:18"
        },
        {
          "start_ref": "40012024",
          "start_ref_usfm": "MAT 12:24",
          "end_ref": "40012024",
          "end_ref_usfm": "MAT 12:24"
        },
        {
          "start_ref": "40012032",
          "start_ref_usfm": "MAT 12:32",
          "end_ref": "40012032",
          "end_ref_usfm": "MAT 12:32"
        },
        {
          "start_ref": "42007033",
          "start_ref_usfm": "LUK 7:33",
          "end_ref": "42007033",
          "end_ref_usfm": "LUK 7:33"
        },
        {
          "start_ref": "43003016",
          "start_ref_usfm": "JHN 3:16",
          "end_ref": "43003016",
          "end_ref_usfm": "JHN 3:16"
        },
        {
          "start_ref": "43003018",
          "start_ref_usfm": "JHN 3:18",
          "end_ref": "43003018",
          "end_ref_usfm": "JHN 3:18"
        },
        {
          "start_ref": "43003036",
          "start_ref_usfm": "JHN 3:36",
          "end_ref": "43003036",
          "end_ref_usfm": "JHN 3:36"
        },
        {
          "start_ref": "43007020",
          "start_ref_usfm": "JHN 7:20",
          "end_ref": "43007020",
          "end_ref_usfm": "JHN 7:20"
        },
        {
          "start_ref": "43008048",
          "start_ref_usfm": "JHN 8:48",
          "end_ref": "43008048",
          "end_ref_usfm": "JHN 8:48"
        },
        {
          "start_ref": "43008052",
          "start_ref_usfm": "JHN 8:52",
          "end_ref": "43008052",
          "end_ref_usfm": "JHN 8:52"
        },
        {
          "start_ref": "43010020",
          "start_ref_usfm": "JHN 10:20",
          "end_ref": "43010020",
          "end_ref_usfm": "JHN 10:20"
        },
        {
          "start_ref": "49001007",
          "start_ref_usfm": "EPH 1:7",
          "end_ref": "49001007",
          "end_ref_usfm": "EPH 1:7"
        },
        {
          "start_ref": "62001007",
          "start_ref_usfm": "1JN 1:7",
          "end_ref": "62001007",
          "end_ref_usfm": "1JN 1:7"
        },
        {
          "start_ref": "62005012",
          "start_ref_usfm": "1JN 5:12",
          "end_ref": "62005012",
          "end_ref_usfm": "1JN 5:12"
        },
        {
          "start_ref": "62005016",
          "start_ref_usfm": "1JN 5:16",
          "end_ref": "62005016",
          "end_ref_usfm": "1JN 5:16"
        },
        {
          "start_ref": "66020015",
          "start_ref_usfm": "REV 20:15",
          "end_ref": "66020015",
          "end_ref_usfm": "REV 20:15"
        },
        {
          "start_ref": "66021008",
          "start_ref_usfm": "REV 21:8",
          "end_ref": "66021008",
          "end_ref_usfm": "REV 21:8"
        },
        {
          "start_ref": "40012031",
          "start_ref_usfm": "MAT 12:31",
          "end_ref": "40012032",
          "end_ref_usfm": "MAT 12:32"
        },
        {
          "start_ref": "41003028",
          "start_ref_usfm": "MRK 3:28",
          "end_ref": "41003030",
          "end_ref_usfm": "MRK 3:30"
        },
        {
          "start_ref": "42011014",
          "start_ref_usfm": "LUK 11:14",
          "end_ref": "42011020",
          "end_ref_usfm": "LUK 11:20"
        },
        {
          "start_ref": "62005016",
          "start_ref_usfm": "1JN 5:16",
          "end_ref": "62005017",
          "end_ref_usfm": "1JN 5:17"
        }
      ],
      "resource": []
    }
  }
]