[
  {
    "content_id": 369086,
    "reference_id": 5673,
    "title": "Yustus",
    "media_type": "Text",
    "index_reference": "yustus",
    "language": "ind",
    "content": "<h1>Yustus</h1><p>1. Nama lain untuk Yusuf Barsabas (<a href=\"https://ref.ly/Acts1:23\">Kisah 1:23</a>). <em>Lihat</em> <span data-bnType=\"resourceReference\" data-resourceId=\"5617\" data-resourceType=\"TyndaleBibleDictionary\">Yusuf #12</span>.</p><p>2. Orang Korintus yang saleh (diduga seorang yang bertobat karena Paulus), yang membuka rumahnya untuk Paulus dan orang-orang Kristen setelah sinagoge Yahudi tidak lagi menerima khotbah Paulus (<a href=\"https://ref.ly/Acts18:7\">Kisah 18:7</a>). Ada perbedaan di antara manuskrip mengenai bentuk pasti nama tersebut. Berbagai ejaan menyebutkan Yustus atau Titius Yustus. Dia juga diidentifikasi sebagai Gayus dalam <a href=\"https://ref.ly/Rom16:23\">Rm. 16:23</a>.</p><p>3. Nama keluarga seorang percaya bernama Yesus, seorang Kristen Yahudi (<a href=\"https://ref.ly/Col4:11\">Kol. 4:11</a>). <em>Lihat</em> <span data-bnType=\"resourceReference\" data-resourceId=\"5524\" data-resourceType=\"TyndaleBibleDictionary\">Yesus #3</span>.</p>",
    "associations": {
      "passage": [
        {
          "start_ref": "44001023",
          "start_ref_usfm": "ACT 1:23",
          "end_ref": "44001023",
          "end_ref_usfm": "ACT 1:23"
        },
        {
          "start_ref": "44018007",
          "start_ref_usfm": "ACT 18:7",
          "end_ref": "44018007",
          "end_ref_usfm": "ACT 18:7"
        },
        {
          "start_ref": "45016023",
          "start_ref_usfm": "ROM 16:23",
          "end_ref": "45016023",
          "end_ref_usfm": "ROM 16:23"
        },
        {
          "start_ref": "51004011",
          "start_ref_usfm": "COL 4:11",
          "end_ref": "51004011",
          "end_ref_usfm": "COL 4:11"
        }
      ],
      "resource": [
        {
          "reference_id": 5617,
          "content_id": 369082,
          "resource_code": "TyndaleBibleDictionary",
          "label": "Yusuf",
          "language": "ind"
        }
      ]
    }
  }
]